pygramed/__init__.py
pygramedia-0.0.2.dist-info/METADATA
pygramedia-0.0.2.dist-info/RECORD
pygramedia-0.0.2.dist-info/WHEEL
pygramedia-0.0.2.dist-info/top_level.txt
